libvirttestapi/__init__.py
libvirttestapi/main.py
libvirttestapi/repos/__init__.py
libvirttestapi/repos/checkpoint/__init__.py
libvirttestapi/repos/checkpoint/checkpoint.py
libvirttestapi/repos/checkpoint/checkpoint_create.py
libvirttestapi/repos/checkpoint/checkpoint_delete.py
libvirttestapi/repos/checkpoint/checkpoint_get_parent.py
libvirttestapi/repos/checkpoint/checkpoint_get_xml.py
libvirttestapi/repos/checkpoint/checkpoint_lookup.py
libvirttestapi/repos/checkpoint/checkpoint_negative.py
libvirttestapi/repos/checkpoint/list_all_checkpoints.py
libvirttestapi/repos/checkpoint/list_all_children.py
libvirttestapi/repos/domain/__init__.py
libvirttestapi/repos/domain/abort_job.py
libvirttestapi/repos/domain/add_iothread.py
libvirttestapi/repos/domain/attach_disk.py
libvirttestapi/repos/domain/attach_interface.py
libvirttestapi/repos/domain/autostart.py
libvirttestapi/repos/domain/balloon_memory.py
libvirttestapi/repos/domain/baseline_hypervisor_cpu.py
libvirttestapi/repos/domain/blkstats.py
libvirttestapi/repos/domain/blkstatsflags.py
libvirttestapi/repos/domain/block_commit.py
libvirttestapi/repos/domain/block_copy.py
libvirttestapi/repos/domain/block_iotune.py
libvirttestapi/repos/domain/block_job_abort.py
libvirttestapi/repos/domain/block_job_info.py
libvirttestapi/repos/domain/block_job_set_speed.py
libvirttestapi/repos/domain/block_peek.py
libvirttestapi/repos/domain/block_pull.py
libvirttestapi/repos/domain/block_rebase.py
libvirttestapi/repos/domain/block_resize.py
libvirttestapi/repos/domain/compare_hypervisor_cpu.py
libvirttestapi/repos/domain/console_callback.py
libvirttestapi/repos/domain/console_io.py
libvirttestapi/repos/domain/console_mutex.py
libvirttestapi/repos/domain/control_info.py
libvirttestapi/repos/domain/coredump_with_format.py
libvirttestapi/repos/domain/cpu_affinity.py
libvirttestapi/repos/domain/cpu_hotplug.py
libvirttestapi/repos/domain/cpu_status.py
libvirttestapi/repos/domain/cpu_topology.py
libvirttestapi/repos/domain/create.py
libvirt_test_api-3.0.dist-info/AUTHORS
libvirt_test_api-3.0.dist-info/LICENSE
libvirt_test_api-3.0.dist-info/METADATA
libvirt_test_api-3.0.dist-info/WHEEL
libvirt_test_api-3.0.dist-info/entry_points.txt
libvirt_test_api-3.0.dist-info/top_level.txt
libvirt_test_api-3.0.dist-info/RECORD
