Metadata-Version: 2.1
Name: libvirt-test-api
Version: 3.0
Summary: Python based regression tests for libvirt API
Home-page: https://github.com/libvirt/libvirt-test-API
Author: Libvirt QE Team
Author-email: lnie@redhat.com
License: GPLv2
Platform: UNKNOWN
Requires-Dist: pexpect
